README.md
setup.py
pulumi_gitea/__init__.py
pulumi_gitea/_utilities.py
pulumi_gitea/access_token.py
pulumi_gitea/fork.py
pulumi_gitea/get_org.py
pulumi_gitea/get_repo.py
pulumi_gitea/get_user.py
pulumi_gitea/git_hook.py
pulumi_gitea/oauth2_app.py
pulumi_gitea/org.py
pulumi_gitea/provider.py
pulumi_gitea/public_key.py
pulumi_gitea/pulumi-plugin.json
pulumi_gitea/py.typed
pulumi_gitea/repository.py
pulumi_gitea/repository_key.py
pulumi_gitea/team.py
pulumi_gitea/user.py
pulumi_gitea.egg-info/PKG-INFO
pulumi_gitea.egg-info/SOURCES.txt
pulumi_gitea.egg-info/dependency_links.txt
pulumi_gitea.egg-info/not-zip-safe
pulumi_gitea.egg-info/requires.txt
pulumi_gitea.egg-info/top_level.txt
pulumi_gitea/config/__init__.py
pulumi_gitea/config/vars.py