Metadata-Version: 2.1
Name: pulumi-gitea
Version: 0.0.3
Summary: A Pulumi package for creating and managing Gitea resources
Home-page: https://github.com/MaienM/pulumi-gitea
License: Apache-2.0
Project-URL: Repository, https://github.com/MaienM/pulumi-gitea
Keywords: pulumi gitea category/infrastructure
Platform: UNKNOWN
Requires-Python: >=3.7
